<?xml version="1.0" encoding="UTF-8"?>
<plugin_manifest xmlns="http://www.elgg.org/plugin_manifest/1.8">
	<name>Kpax List</name>
	<id>kPaxList</id>
  <author>Javier Ramirez @javierrami</author>
	<version>0.1</version>
	<category>bundled</category>
	<category>social</category>
	<description>Enables users to search in kPax server</description>
	<website>http://www.jramirez.com.es/</website>
	<copyright>See COPYRIGHT.txt</copyright>
	<license>GNU Public License version 3</license>
	<requires>
		<type>elgg_release</type>
		<version>1.9</version>
	</requires>
	<requires>
		<type>plugin</type>
		<name>kPAX_core</name>
		<version>1.5</version>
	</requires>
	<requires>
		<type>priority</type>
		<priority>after</priority>
		<plugin>kPAX_core</plugin>
	</requires>
	<activate_on_install>false</activate_on_install>
	<admin_interface>advanced</admin_interface>
</plugin_manifest>
